uipath_scaffold/__init__.py
uipath_scaffold/__main__.py
uipath_scaffold/cli.py
uipath_scaffold/generators_helper.py
uipath_scaffold-0.0.7.dist-info/LICENSE
uipath_scaffold-0.0.7.dist-info/METADATA
uipath_scaffold-0.0.7.dist-info/WHEEL
uipath_scaffold-0.0.7.dist-info/top_level.txt
uipath_scaffold-0.0.7.dist-info/RECORD
