Metadata-Version: 2.1
Name: uipath-scaffold
Version: 0.0.7
Summary: CLI tool for running UiPath Scaffold Generators.
Home-page: https://github.com/christianblandford/UiPath-Scaffold
Author: Christian Blandford
Author-email: christianblandford@me.com
License: UNKNOWN
Platform: UNKNOWN
Classifier: Programming Language :: Python :: 3
Classifier: License :: OSI Approved :: MIT License
Classifier: Operating System :: OS Independent
Requires-Dist: console-functions (>=0.0.8)
